virtualcrypto/__init__.py
virtualcrypto/async_client.py
virtualcrypto/client.py
virtualcrypto/errors.py
virtualcrypto/structs.py
virtualcrypto/virtualcrypto.py
virtualcrypto-0.1.3.dist-info/AUTHORS.rst
virtualcrypto-0.1.3.dist-info/LICENSE
virtualcrypto-0.1.3.dist-info/METADATA
virtualcrypto-0.1.3.dist-info/WHEEL
virtualcrypto-0.1.3.dist-info/top_level.txt
virtualcrypto-0.1.3.dist-info/RECORD
