Metadata-Version: 2.1
Name: virtualcrypto
Version: 0.1.3
Summary: VirtualCrypto Python SDK
Home-page: https://github.com/virtualCrypto-discord/virtualcrypto-python
Author: sizumita
Author-email: contact@sumidora.com
License: MIT license
Keywords: virtualcrypto
Platform: UNKNOWN
Classifier: Development Status :: 2 - Pre-Alpha
Classifier: Intended Audience :: Developers
Classifier: License :: OSI Approved :: MIT License
Classifier: Natural Language :: English
Classifier: Programming Language :: Python :: 3
Classifier: Programming Language :: Python :: 3.6
Classifier: Programming Language :: Python :: 3.7
Classifier: Programming Language :: Python :: 3.8
Requires-Python: >=3.6
Requires-Dist: requests
Requires-Dist: aiohttp
